pydantic_partials/__init__.py
pydantic_partials/config.py
pydantic_partials/make_missing_falsy.py
pydantic_partials/meta.py
pydantic_partials/partial.py
pydantic_partials/py.typed
pydantic_partials/sentinels.py
pydantic_partials-4.0.0.dist-info/METADATA
pydantic_partials-4.0.0.dist-info/WHEEL
pydantic_partials-4.0.0.dist-info/licenses/LICENSE
pydantic_partials-4.0.0.dist-info/RECORD
