Metadata-Version: 2.4
Name: pydantic-partials
Version: 4.0.0
Summary: Pydantic partial model class, with ability to easily dynamically omit fields when serializing a model.
License-File: LICENSE
Author: Josh Orr
Author-email: josh@orr.blue
Requires-Python: >=3.10,<4.0
Classifier: License :: OSI Approved :: The Unlicense (Unlicense)
Classifier: Programming Language :: Python :: 3
Classifier: Programming Language :: Python :: 3.10
Classifier: Programming Language :: Python :: 3.11
Classifier: Programming Language :: Python :: 3.12
Classifier: Programming Language :: Python :: 3.13
Classifier: Programming Language :: Python :: 3.14
Classifier: Topic :: Software Development :: Libraries :: Python Modules
Requires-Dist: pydantic (>=2.12.5,<3.0.0)
Requires-Dist: xsentinels (>=1.3.1,<2.0.0)
Project-URL: Repository, https://github.com/joshorr/pydantic-partials
